pyspecter/__init__.py
pyspecter/pyspecter.py
pyspecter-0.1.1.dist-info/LICENSE
pyspecter-0.1.1.dist-info/METADATA
pyspecter-0.1.1.dist-info/WHEEL
pyspecter-0.1.1.dist-info/top_level.txt
pyspecter-0.1.1.dist-info/RECORD
