Metadata-Version: 2.1
Name: pyspecter
Version: 0.1.1
Summary: A library to query nested data in Python
Home-page: https://github.com/yellowbean/pyspecter
Author: Xiaoyu Zhang
Author-email: always.zhang@gmail.com
Classifier: Programming Language :: Python :: 3
Classifier: License :: OSI Approved :: MIT License
Classifier: Operating System :: OS Independent
Requires-Python: >=3.10
License-File: LICENSE
